iprm/CMakeLists.txt
iprm/__init__.py
iprm/main.py
iprm/api/__init__.py
iprm/api/namespace.py
iprm/api/obj/__init__.py
iprm/api/obj/cxx.py
iprm/api/obj/project.py
iprm/api/obj/rust.py
iprm/api/obj/subdirectories.py
iprm/api/obj/target.py
iprm/build/_deps/pybind11-src/noxfile.py
iprm/build/_deps/pybind11-src/setup.py
iprm/build/_deps/pybind11-src/docs/benchmark.py
iprm/build/_deps/pybind11-src/docs/conf.py
iprm/build/_deps/pybind11-src/pybind11/__init__.py
iprm/build/_deps/pybind11-src/pybind11/__main__.py
iprm/build/_deps/pybind11-src/pybind11/_version.py
iprm/build/_deps/pybind11-src/pybind11/commands.py
iprm/build/_deps/pybind11-src/pybind11/py.typed
iprm/build/_deps/pybind11-src/pybind11/setup_helpers.py
iprm/build/_deps/pybind11-src/tests/conftest.py
iprm/build/_deps/pybind11-src/tests/env.py
iprm/build/_deps/pybind11-src/tests/test_async.py
iprm/build/_deps/pybind11-src/tests/test_buffers.py
iprm/build/_deps/pybind11-src/tests/test_builtin_casters.py
iprm/build/_deps/pybind11-src/tests/test_call_policies.py
iprm/build/_deps/pybind11-src/tests/test_callbacks.py
iprm/build/_deps/pybind11-src/tests/test_chrono.py
iprm/build/_deps/pybind11-src/tests/test_class.py
iprm/build/_deps/pybind11-src/tests/test_const_name.py
iprm/build/_deps/pybind11-src/tests/test_constants_and_functions.py
iprm/build/_deps/pybind11-src/tests/test_copy_move.py
iprm/build/_deps/pybind11-src/tests/test_cpp_conduit.py
iprm/build/_deps/pybind11-src/tests/test_custom_type_casters.py
iprm/build/_deps/pybind11-src/tests/test_custom_type_setup.py
iprm/build/_deps/pybind11-src/tests/test_docstring_options.py
iprm/build/_deps/pybind11-src/tests/test_eigen_matrix.py
iprm/build/_deps/pybind11-src/tests/test_eigen_tensor.py
iprm/build/_deps/pybind11-src/tests/test_enum.py
iprm/build/_deps/pybind11-src/tests/test_eval.py
iprm/build/_deps/pybind11-src/tests/test_eval_call.py
iprm/build/_deps/pybind11-src/tests/test_exceptions.py
iprm/build/_deps/pybind11-src/tests/test_factory_constructors.py
iprm-0.0.1.dist-info/LICENSE
iprm-0.0.1.dist-info/METADATA
iprm-0.0.1.dist-info/WHEEL
iprm-0.0.1.dist-info/entry_points.txt
iprm-0.0.1.dist-info/top_level.txt
iprm-0.0.1.dist-info/RECORD
