Metadata-Version: 2.2
Name: iprm
Version: 0.0.1
Summary: Intermediate Project Representation Model
Classifier: Programming Language :: Python :: 3
Classifier: Operating System :: OS Independent
Requires-Python: >=3.12
License-File: LICENSE
